CHANGELOG.rst
CONTRIBUTING.rst
DESCRIPTION.rst
LICENSE
MANIFEST.in
README.rst
setup.cfg
setup.py
binstarsolver/__init__.py
binstarsolver/main.py
binstarsolver/utils.py
binstarsolver.egg-info/PKG-INFO
binstarsolver.egg-info/SOURCES.txt
binstarsolver.egg-info/dependency_links.txt
binstarsolver.egg-info/entry_points.txt
binstarsolver.egg-info/requires.txt
binstarsolver.egg-info/top_level.txt
docs/Makefile
docs/binstarsolver.rst
docs/conf.py
docs/index.rst
docs/make.bat
docs/modules.rst
docs/requirements_readthedocs.txt
docs/_build/html/_sources/binstarsolver.txt
docs/_build/html/_sources/index.txt
docs/_build/html/_sources/modules.txt
tests/test_main.py
tests/test_utils.py