Metadata-Version: 1.1
Name: binstarsolver
Version: 0.1.3
Summary: Estimate physical quantities of a binary star system from observed quantities.
Home-page: http://binstarsolver.readthedocs.org
Author: Samuel Harrold; White Dwarf Research Group, Astronomy Dept, UT Austin
Author-email: samuel.harrold@gmail.com
License: MIT
Keywords: astronomy astrophysics binary stars observing
Platform: UNKNOWN
Classifier: Development Status :: 3 - Alpha
Classifier: Intended Audience :: Science/Research
Classifier: Topic :: Scientific/Engineering :: Astronomy
Classifier: License :: OSI Approved :: MIT License
Classifier: Programming Language :: Python :: 2
Classifier: Programming Language :: Python :: 2.7
Classifier: Programming Language :: Python :: 3
Classifier: Programming Language :: Python :: 3.4
